relexi/__init__.py
relexi/env/__init__.py
relexi/env/flexiEnvSmartSim.py
relexi/io/__init__.py
relexi/io/output.py
relexi/io/readin.py
relexi/rl/__init__.py
relexi/rl/models.py
relexi/rl/ppo/__init__.py
relexi/rl/ppo/train.py
relexi/rl/tf_helpers.py
relexi/runtime/__init__.py
relexi/runtime/helpers.py
relexi/runtime/launch_configuration.py
relexi/runtime/runtime.py
relexi/scripts/__init__.py
relexi/scripts/relexi_cli.py
relexi-2.0.0.dist-info/LICENSE.md
relexi-2.0.0.dist-info/METADATA
relexi-2.0.0.dist-info/WHEEL
relexi-2.0.0.dist-info/entry_points.txt
relexi-2.0.0.dist-info/RECORD
