Metadata-Version: 2.1
Name: relexi
Version: 2.0.0
Summary: A reinforcement learning library for simulation environments on high-performance computing systems.
Home-page: https://flexi-framework.github.io/relexi/
License: GPL-3.0-or-later
Keywords: reinforcement learning,machine learning,high-performance computing,simulation
Author: Marius Kurz
Author-email: marius.kurz@cwi.nl
Classifier: Development Status :: 4 - Beta
Classifier: License :: OSI Approved :: GNU General Public License v3 (GPLv3)
Classifier: License :: OSI Approved :: GNU General Public License v3 or later (GPLv3+)
Classifier: Operating System :: OS Independent
Classifier: Programming Language :: Python :: 2
Classifier: Programming Language :: Python :: 2.7
Classifier: Programming Language :: Python :: 3
Classifier: Programming Language :: Python :: 3.4
Classifier: Programming Language :: Python :: 3.5
Classifier: Programming Language :: Python :: 3.6
Classifier: Programming Language :: Python :: 3.7
Classifier: Programming Language :: Python :: 3.8
Classifier: Programming Language :: Python :: 3.9
Classifier: Programming Language :: Python :: 3.10
Classifier: Programming Language :: Python :: 3.11
Classifier: Programming Language :: Python :: 3.12
Requires-Dist: cmake
Requires-Dist: matplotlib
Requires-Dist: pdoc
Requires-Dist: pytest
Requires-Dist: pytest-cov
Requires-Dist: pyyaml
Requires-Dist: setuptools (!=70.*)
Requires-Dist: smartredis
Requires-Dist: smartsim (>=0.4,<0.7)
Requires-Dist: tensorflow (>=2.15,<2.16)
Requires-Dist: tf-agents
Project-URL: Documentation, https://flexi-framework.github.io/relexi/
Project-URL: Repository, https://github.com/flexi-framework/relexi/
